{
  "questions": [
    {
      "question_id": 119,
      "content_block_id": 45,
      "question": "Where is the Immigration Directorate of the Bucharest Municipality located?"
    },
    {
      "question_id": 120,
      "content_block_id": 45,
      "question": "What services does the Immigration Service Ilfov County provide?"
    },
    {
      "question_id": 121,
      "content_block_id": 45,
      "question": "Who is responsible for accommodation and procedures for asylum seekers in Bucharest?"
    },
    {
      "question_id": 122,
      "content_block_id": 46,
      "question": "Who is responsible for managing the regional centres?"
    },
    {
      "question_id": 123,
      "content_block_id": 46,
      "question": "What types of individuals do these centres accommodate and process?"
    },
    {
      "question_id": 124,
      "content_block_id": 46,
      "question": "Where are the headquarters of the Regional Centre located?"
    },
    {
      "question_id": 125,
      "content_block_id": 47,
      "question": "What is the location of the Centrul Regional de Proceduri și Cazare?"
    },
    {
      "question_id": 126,
      "content_block_id": 47,
      "question": "Who can access the Serviciul pentru Imigrări al Județului Bacău?"
    },
    {
      "question_id": 127,
      "content_block_id": 47,
      "question": "Where is the Biroul pentru Imigrări al Județului Brăila located?"
    }
  ]
}