{
  "questions": [
    {
      "question_id": 319,
      "content_block_id": 13,
      "question": "What services are available for asylum seekers?"
    },
    {
      "question_id": 320,
      "content_block_id": 13,
      "question": "What are the regional procedures related to immigration?"
    },
    {
      "question_id": 321,
      "content_block_id": 13,
      "question": "How can someone contact the relevant immigration authorities?"
    },
    {
      "question_id": 322,
      "content_block_id": 13,
      "question": "When seeking asylum, what is the general process?"
    },
    {
      "question_id": 323,
      "content_block_id": 13,
      "question": "What are the locations of different immigration offices?"
    }
  ]
}