{
  "questions": [
    {
      "question_id": 391,
      "content_block_id": 40,
      "question": "What types of support are offered to refugees?"
    },
    {
      "question_id": 392,
      "content_block_id": 40,
      "question": "What is the purpose of 'Law made simple'?"
    },
    {
      "question_id": 393,
      "content_block_id": 40,
      "question": "How does 'PTSD Help' assist individuals?"
    },
    {
      "question_id": 394,
      "content_block_id": 40,
      "question": "Are hospital services provided free of charge, or is there a cost?"
    },
    {
      "question_id": 395,
      "content_block_id": 40,
      "question": "What are the main differences between public and private hospital care?"
    },
    {
      "question_id": 396,
      "content_block_id": 40,
      "question": "In which cities are support services available?"
    },
    {
      "question_id": 397,
      "content_block_id": 40,
      "question": "What are the requirements for accessing hospital services?"
    },
    {
      "question_id": 398,
      "content_block_id": 40,
      "question": "Can one get assistance for Post Traumatic Stress Disorder?"
    },
    {
      "question_id": 399,
      "content_block_id": 40,
      "question": "Who is responsible for providing the 'Dopomoha' solutions?"
    },
    {
      "question_id": 400,
      "content_block_id": 40,
      "question": "What kinds of medical conditions qualify for one-day hospitalization?"
    }
  ]
}