{
  "questions": [
    {
      "question_id": 662,
      "content_block_id": 63,
      "question": "Where can newcomers in Oradea find help and important contacts?"
    },
    {
      "question_id": 663,
      "content_block_id": 63,
      "question": "How can one contact the Bihor County Immigration Service?"
    },
    {
      "question_id": 664,
      "content_block_id": 63,
      "question": "What is the emergency call number in Romania?"
    },
    {
      "question_id": 665,
      "content_block_id": 63,
      "question": "Are there contact numbers for the National Anti-Traffic Hotline in Romania?"
    },
    {
      "question_id": 666,
      "content_block_id": 63,
      "question": "What information is needed for the accommodation, board, and integration support program in Oradea?"
    },
    {
      "question_id": 667,
      "content_block_id": 63,
      "question": "How can tickets for public transport in Oradea be purchased?"
    },
    {
      "question_id": 668,
      "content_block_id": 63,
      "question": "Where can one go for medical services in Oradea?"
    },
    {
      "question_id": 669,
      "content_block_id": 63,
      "question": "Is a list of family doctors available in Oradea?"
    },
    {
      "question_id": 670,
      "content_block_id": 63,
      "question": "Which organizations provide psychological support in Oradea?"
    },
    {
      "question_id": 671,
      "content_block_id": 63,
      "question": "What languages does the International Organization for Migration (IOM) offer psychological support in?"
    },
    {
      "question_id": 672,
      "content_block_id": 63,
      "question": "Does Plan International Organization offer psychological assistance for Ukrainian refugees?"
    },
    {
      "question_id": 673,
      "content_block_id": 63,
      "question": "How can a child be enrolled in primary education in Oradea?"
    },
    {
      "question_id": 674,
      "content_block_id": 63,
      "question": "What documents are required for child enrollment in primary education?"
    },
    {
      "question_id": 675,
      "content_block_id": 63,
      "question": "What educational programs does the the Oradea Caritas Eparhial Association organize?"
    },
    {
      "question_id": 676,
      "content_block_id": 63,
      "question": "What services does the Women's Center in Oradea provide?"
    },
    {
      "question_id": 677,
      "content_block_id": 63,
      "question": "Are free and confidential HIV services available in Romania?"
    },
    {
      "question_id": 678,
      "content_block_id": 63,
      "question": "Where can I find out more about healthcare services in Romania?"
    }
  ]
}